{"data":{"Jax":{"id":24,"key":"Jax","name":"Jax","title":"gran maestro d'armi","skins":[{"id":24000,"name":"default","num":0},{"id":24001,"name":"Il Possente Jax","num":1},{"id":24002,"name":"Jax Vandalo","num":2},{"id":24003,"name":"Jax Pescatore","num":3},{"id":24004,"name":"PAX Jax","num":4},{"id":24005,"name":"Jaximus","num":5},{"id":24006,"name":"Jax del Tempio","num":6},{"id":24007,"name":"Nemesi Jax","num":7},{"id":24008,"name":"Jax SKT T1","num":8},{"id":24012,"name":"Jax Inquisitore","num":12}]},"Sona":{"id":37,"key":"Sona","name":"Sona","title":"maestra delle corde","skins":[{"id":37000,"name":"default","num":0},{"id":37001,"name":"Musa Sona","num":1},{"id":37002,"name":"Sona dei Pentakill","num":2},{"id":37003,"name":"Sona Astro del Ciel","num":3},{"id":37004,"name":"Sona Guqin","num":4},{"id":37005,"name":"Sona Arcade","num":5},{"id":37006,"name":"DJ Sona","num":6},{"id":37007,"name":"Sona del Cuore","num":7}]},"Tristana":{"id":18,"key":"Tristana","name":"Tristana","title":"l'artigliere degli yordle","skins":[{"id":18000,"name":"default","num":0},{"id":18001,"name":"Tristana Ragazza Riot","num":1},{"id":18002,"name":"Tristana Elfa Onesta","num":2},{"id":18003,"name":"Tristana Pompiere","num":3},{"id":18004,"name":"Tristana Guerrigliera","num":4},{"id":18005,"name":"Tristana Piratessa","num":5},{"id":18006,"name":"Tristana Ragazza Razzo","num":6},{"id":18010,"name":"Tristana Addestratrice di Draghi","num":10},{"id":18011,"name":"Strega Tristana","num":11},{"id":18012,"name":"Tristana Squadra Omega","num":12}]},"Varus":{"id":110,"key":"Varus","name":"Varus","title":"la freccia del castigo","skins":[{"id":110000,"name":"default","num":0},{"id":110001,"name":"Varus Cristalli del Flagello","num":1},{"id":110002,"name":"Varus della Luce","num":2},{"id":110003,"name":"Varus Operazioni Artiche","num":3},{"id":110004,"name":"Varus Cerca Cuori","num":4},{"id":110005,"name":"Varus Dardolesto","num":5},{"id":110006,"name":"Varus Stella Oscura","num":6}]},"Fiora":{"id":114,"key":"Fiora","name":"Fiora","title":"la magnifica duellante","skins":[{"id":114000,"name":"default","num":0},{"id":114001,"name":"Fiora Guardia Reale","num":1},{"id":114002,"name":"Fiora Corvo Notturno","num":2},{"id":114003,"name":"Fiora Preside","num":3},{"id":114004,"name":"PROGETTO: Fiora","num":4},{"id":114005,"name":"Fiora Festa in Piscina","num":5},{"id":114022,"name":"Fiora Spada Alata","num":22}]},"Singed":{"id":27,"key":"Singed","name":"Singed","title":"il folle chimico","skins":[{"id":27000,"name":"default","num":0},{"id":27001,"name":"Riot Singed","num":1},{"id":27002,"name":"Singed Hextech","num":2},{"id":27003,"name":"Singed Surfista","num":3},{"id":27004,"name":"Singed Scienziato Pazzo","num":4},{"id":27005,"name":"Singed Potenziato","num":5},{"id":27006,"name":"Singed della Nevicata","num":6},{"id":27007,"name":"Singed SSW","num":7},{"id":27008,"name":"Singed Piaga oscura","num":8},{"id":27009,"name":"Singed Apicultore","num":9}]},"TahmKench":{"id":223,"key":"TahmKench","name":"Tahm Kench","title":"il re del fiume","skins":[{"id":223000,"name":"default","num":0},{"id":223001,"name":"Tahm Kench Master Chef","num":1},{"id":223002,"name":"Urf Kench","num":2}]},"Leblanc":{"id":7,"key":"Leblanc","name":"LeBlanc","title":"l'ingannatrice","skins":[{"id":7000,"name":"default","num":0},{"id":7001,"name":"Crudelia LeBlanc","num":1},{"id":7002,"name":"La Prestigiosa LeBlanc","num":2},{"id":7003,"name":"LeBlanc del Vischio","num":3},{"id":7004,"name":"LeBlanc Figlia dei Corvi","num":4},{"id":7005,"name":"LeBlanc del Bosco Antico","num":5}]},"Thresh":{"id":412,"key":"Thresh","name":"Thresh","title":"Il carceriere","skins":[{"id":412000,"name":"default","num":0},{"id":412001,"name":"Thresh Terrore Profondo","num":1},{"id":412002,"name":"Thresh Stagione 2013","num":2},{"id":412003,"name":"Thresh Luna di Sangue","num":3},{"id":412004,"name":"Thresh SSW","num":4},{"id":412005,"name":"Thresh Stella Oscura","num":5}]},"Karma":{"id":43,"key":"Karma","name":"Karma","title":"l'illuminata","skins":[{"id":43000,"name":"default","num":0},{"id":43001,"name":"Karma Dea del Sole","num":1},{"id":43002,"name":"Sakura Karma","num":2},{"id":43003,"name":"Karma Tradizionale","num":3},{"id":43004,"name":"Karma Ordine del Loto","num":4},{"id":43005,"name":"Karma Inquisitrice","num":5},{"id":43006,"name":"Karma Prodigio Invernale","num":6},{"id":43007,"name":"Karma Conquistatrice","num":7}]},"Jhin":{"id":202,"key":"Jhin","name":"Jhin","title":"il virtuoso","skins":[{"id":202000,"name":"default","num":0},{"id":202001,"name":"Jhin Mezzogiorno di Fuoco","num":1},{"id":202002,"name":"Jhin Luna di Sangue","num":2},{"id":202003,"name":"Jhin SKT T1","num":3}]},"Rumble":{"id":68,"key":"Rumble","name":"Rumble","title":"la minaccia meccanizzata","skins":[{"id":68000,"name":"default","num":0},{"id":68001,"name":"Rumble Tropicale","num":1},{"id":68002,"name":"Rumble Topo da Stiva","num":2},{"id":68003,"name":"Rumble Megagalattico","num":3}]},"Udyr":{"id":77,"key":"Udyr","name":"Udyr","title":"l'eremita spirituale","skins":[{"id":77000,"name":"default","num":0},{"id":77001,"name":"Udyr Cintura Nera","num":1},{"id":77002,"name":"Udyr Primordiale","num":2},{"id":77003,"name":"Udyr Guardia Spirituale","num":3},{"id":77004,"name":"Sicuramente non Udyr","num":4}]},"LeeSin":{"id":64,"key":"LeeSin","name":"Lee Sin","title":"il monaco cieco","skins":[{"id":64000,"name":"default","num":0},{"id":64001,"name":"Lee Sin Tradizionale","num":1},{"id":64002,"name":"Lee Sin Accolito","num":2},{"id":64003,"name":"Lee Sin Pugno del Drago","num":3},{"id":64004,"name":"Lee Sin Muay Thai","num":4},{"id":64005,"name":"Lee Sin Festa in Piscina","num":5},{"id":64006,"name":"Lee Sin SKT T1","num":6},{"id":64010,"name":"Lee Sin KO","num":10},{"id":64011,"name":"Lee Sin Pugno Divino","num":11}]},"Yorick":{"id":83,"key":"Yorick","name":"Yorick","title":"Il pastore delle anime perdute","skins":[{"id":83000,"name":"default","num":0},{"id":83001,"name":"Yorick Becchino","num":1},{"id":83002,"name":"Yorick dei Pentakill","num":2},{"id":83003,"name":"Yorick della Luce","num":3}]},"Ornn":{"id":516,"key":"Ornn","name":"Ornn","title":"il fuoco della montagna","skins":[{"id":516000,"name":"default","num":0},{"id":516001,"name":"Ornn Signore del Tuono","num":1}]},"Kayn":{"id":141,"key":"Kayn","name":"Kayn","title":"il mietitore d'ombra","skins":[{"id":141000,"name":"default","num":0},{"id":141001,"name":"Kayn Cacciatore d'anime","num":1}]},"Kassadin":{"id":38,"key":"Kassadin","name":"Kassadin","title":"il camminatore del Vuoto","skins":[{"id":38000,"name":"default","num":0},{"id":38001,"name":"Kassadin del Festival","num":1},{"id":38002,"name":"Kassadin Abitante del Profondo","num":2},{"id":38003,"name":"Kassadin Prima del Vuoto","num":3},{"id":38004,"name":"Kassadin Messaggero","num":4},{"id":38005,"name":"Kassadin Mietitore Cosmico","num":5}]},"Sivir":{"id":15,"key":"Sivir","name":"Sivir","title":"la signora delle battaglie","skins":[{"id":15000,"name":"default","num":0},{"id":15001,"name":"Sivir Principessa Guerriera","num":1},{"id":15002,"name":"Sivir Spettacolare","num":2},{"id":15003,"name":"Sivir Cacciatrice","num":3},{"id":15004,"name":"Sivir Banditessa","num":4},{"id":15005,"name":"PAX Sivir","num":5},{"id":15006,"name":"Sivir Tempesta di Neve","num":6},{"id":15007,"name":"Sivir Inquisitrice","num":7},{"id":15008,"name":"Sivir Vittoriosa","num":8},{"id":15009,"name":"Neo PAX Sivir","num":9}]},"MissFortune":{"id":21,"key":"MissFortune","name":"Miss Fortune","title":"la cacciatrice di taglie","skins":[{"id":21000,"name":"default","num":0},{"id":21001,"name":"Miss Fortune Cowgirl","num":1},{"id":21002,"name":"Miss Fortune Waterloo","num":2},{"id":21003,"name":"Agente Segreto Miss Fortune","num":3},{"id":21004,"name":"Miss Fortune Bastoncino Zuccherato","num":4},{"id":21005,"name":"Miss Fortune Guerriera della Strada","num":5},{"id":21006,"name":"Miss Fortune Mafiosa","num":6},{"id":21007,"name":"Miss Fortune Arcade","num":7},{"id":21008,"name":"Capitana Fortune","num":8},{"id":21009,"name":"Miss Fortune Festa in Piscina","num":9},{"id":21015,"name":"Miss Fortune Guardiana Stellare","num":15}]},"Draven":{"id":119,"key":"Draven","name":"Draven","title":"il glorioso carnefice","skins":[{"id":119000,"name":"default","num":0},{"id":119001,"name":"Draven Predatore di Anime","num":1},{"id":119002,"name":"Draven Gladiatore","num":2},{"id":119003,"name":"Draven Prima Serata","num":3},{"id":119004,"name":"Draven Festa in Piscina","num":4},{"id":119005,"name":"Draven Cacciatore di Bestie","num":5},{"id":119006,"name":"Draven Draven","num":6}]},"Yasuo":{"id":157,"key":"Yasuo","name":"Yasuo","title":"il reietto","skins":[{"id":157000,"name":"default","num":0},{"id":157001,"name":"Yasuo Mezzogiorno di Fuoco","num":1},{"id":157002,"name":"PROGETTO: Yasuo","num":2},{"id":157003,"name":"Yasuo Luna di Sangue","num":3},{"id":157009,"name":"Yasuo Portatore della Notte","num":9}]},"Kayle":{"id":10,"key":"Kayle","name":"Kayle","title":"la paladina del bene","skins":[{"id":10000,"name":"default","num":0},{"id":10001,"name":"Kayle d'Argento","num":1},{"id":10002,"name":"Kayle Verde Smeraldo","num":2},{"id":10003,"name":"Kayle Smascherata","num":3},{"id":10004,"name":"Kayle Nata per la Battaglia","num":4},{"id":10005,"name":"Kayle del Giudizio","num":5},{"id":10006,"name":"Kayle Ala Eterea","num":6},{"id":10007,"name":"Riot Kayle","num":7},{"id":10008,"name":"Kayle Inquisitrice di ferro","num":8},{"id":10009,"name":"Kayle dei Pentakill","num":9}]},"Shaco":{"id":35,"key":"Shaco","name":"Shaco","title":"il demone giullare","skins":[{"id":35000,"name":"default","num":0},{"id":35001,"name":"Shaco Cappellaio Matto","num":1},{"id":35002,"name":"Shaco Reale","num":2},{"id":35003,"name":"Schiacciashaco","num":3},{"id":35004,"name":"Shaco a Carica","num":4},{"id":35005,"name":"Shaco Psicopatico","num":5},{"id":35006,"name":"Shaco Mascherato","num":6},{"id":35007,"name":"Shaco Jolly ","num":7}]},"Renekton":{"id":58,"key":"Renekton","name":"Renekton","title":"il macellaio delle dune","skins":[{"id":58000,"name":"default","num":0},{"id":58001,"name":"Renekton Galattico","num":1},{"id":58002,"name":"Renekton Dundee","num":2},{"id":58003,"name":"Renekton Furia Sanguinaria","num":3},{"id":58004,"name":"Renekton Guerriero delle Rune","num":4},{"id":58005,"name":"Renekton Terra Bruciata","num":5},{"id":58006,"name":"Renekton Festa in Piscina","num":6},{"id":58007,"name":"Renekton Preistorico","num":7},{"id":58008,"name":"Renekton SKT T1","num":8},{"id":58009,"name":"Renekton Giocattolo","num":9}]},"Hecarim":{"id":120,"key":"Hecarim","name":"Hecarim","title":"l'ombra della guerra","skins":[{"id":120000,"name":"default","num":0},{"id":120001,"name":"Hecarim Cavaliere Sanguinario","num":1},{"id":120002,"name":"Hecarim Mietitore","num":2},{"id":120003,"name":"Hecarim Senza Testa","num":3},{"id":120004,"name":"Hecarim Arcade","num":4},{"id":120005,"name":"Hecarim del Bosco Antico","num":5},{"id":120006,"name":"Hecarim Distruttore del mondo","num":6},{"id":120007,"name":"Hecarim Lanciere Zero","num":7}]},"Fizz":{"id":105,"key":"Fizz","name":"Fizz","title":"il prestigiatore delle maree","skins":[{"id":105000,"name":"default","num":0},{"id":105001,"name":"Fizz Atlantideo","num":1},{"id":105002,"name":"Fizz Tundra","num":2},{"id":105003,"name":"Fizz Pescatore","num":3},{"id":105004,"name":"Fizz del Vuoto","num":4},{"id":105008,"name":"Fizz Coda a Batuffoli","num":8},{"id":105009,"name":"Fizz Megagalattico","num":9},{"id":105010,"name":"Fizz Squadra Omega","num":10}]},"KogMaw":{"id":96,"key":"KogMaw","name":"Kog'Maw","title":"la bocca dell'abisso","skins":[{"id":96000,"name":"default","num":0},{"id":96001,"name":"Kog'Maw Bruco","num":1},{"id":96002,"name":"Kog'Maw del Sonora","num":2},{"id":96003,"name":"Kog'Maw Monarca","num":3},{"id":96004,"name":"Renna Kog'Maw","num":4},{"id":96005,"name":"Kog'Maw Drago Cinese","num":5},{"id":96006,"name":"Kog'Maw delle Profondità","num":6},{"id":96007,"name":"Kog'Maw Giurassico","num":7},{"id":96008,"name":"Kog'Maw Macchina da Guerra","num":8},{"id":96009,"name":"Kog'Bau","num":9}]},"Maokai":{"id":57,"key":"Maokai","name":"Maokai","title":"il treant demoniaco","skins":[{"id":57000,"name":"default","num":0},{"id":57001,"name":"Maokai Ardente","num":1},{"id":57002,"name":"Maokai Totemico","num":2},{"id":57003,"name":"Maokai a Festa","num":3},{"id":57004,"name":"Maokai Infestato","num":4},{"id":57005,"name":"Maokai Portiere ","num":5},{"id":57006,"name":"Miaokai","num":6},{"id":57007,"name":"Maokai Vittorioso","num":7}]},"Lissandra":{"id":127,"key":"Lissandra","name":"Lissandra","title":"la strega dei ghiacci","skins":[{"id":127000,"name":"default","num":0},{"id":127001,"name":"Lissandra Pietra Sanguigna","num":1},{"id":127002,"name":"Lissandra Regina delle Lame","num":2},{"id":127003,"name":"Programma Lissandra","num":3}]},"Jinx":{"id":222,"key":"Jinx","name":"Jinx","title":"la mina vagante","skins":[{"id":222000,"name":"default","num":0},{"id":222001,"name":"Jinx Mafiosa","num":1},{"id":222002,"name":"Jinx Fuoco d'Artificio","num":2},{"id":222003,"name":"Jinx Sopravvissuta","num":3},{"id":222004,"name":"Jinx Guardiana Stellare","num":4}]},"Urgot":{"id":6,"key":"Urgot","name":"Urgot","title":"il dreadnought","skins":[{"id":6000,"name":"default","num":0},{"id":6001,"name":"Granchiobot Grande Nemico","num":1},{"id":6002,"name":"Urgot Macellaio","num":2},{"id":6003,"name":"Urgot Macchina da Guerra","num":3}]},"Fiddlesticks":{"id":9,"key":"Fiddlesticks","name":"Fiddlesticks","title":"il messaggero della sventura","skins":[{"id":9000,"name":"default","num":0},{"id":9001,"name":"Fiddlesticks Spettrale","num":1},{"id":9002,"name":"Fiddlesticks Union Jack","num":2},{"id":9003,"name":"Fiddlesticks Bandito","num":3},{"id":9004,"name":"Fiddlesticks Testa da Zucca","num":4},{"id":9005,"name":"Per la Barba di Fiddle","num":5},{"id":9006,"name":"Fiddlesticks Festa a Sorpresa","num":6},{"id":9007,"name":"Fiddlesticks Dolcetto o Scherzetto","num":7},{"id":9008,"name":"Fiddlesticks Asceso","num":8}]},"Galio":{"id":3,"key":"Galio","name":"Galio","title":"il colosso","skins":[{"id":3000,"name":"default","num":0},{"id":3001,"name":"Galio Incantato","num":1},{"id":3002,"name":"Galio Hextech","num":2},{"id":3003,"name":"Galio Commando","num":3},{"id":3004,"name":"Galio Guardiano","num":4},{"id":3005,"name":"Galio Rubacuori","num":5}]},"Pantheon":{"id":80,"key":"Pantheon","name":"Pantheon","title":"l'artigiano della guerra","skins":[{"id":80000,"name":"default","num":0},{"id":80001,"name":"Pantheon Mirmidone","num":1},{"id":80002,"name":"Pantheon Spietato","num":2},{"id":80003,"name":"Pantheon Perseo","num":3},{"id":80004,"name":"Full Metal Pantheon","num":4},{"id":80005,"name":"Pantheon Guerriero Legionario","num":5},{"id":80006,"name":"Pantheon Ammazzadraghi","num":6},{"id":80007,"name":"Pantheon Sopravvissuto","num":7},{"id":80008,"name":"Pantheon Fornaio","num":8}]},"Talon":{"id":91,"key":"Talon","name":"Talon","title":"l'ombra della lama","skins":[{"id":91000,"name":"default","num":0},{"id":91001,"name":"Talon Rinnegato","num":1},{"id":91002,"name":"Talon dell'Élite Cremisi","num":2},{"id":91003,"name":"Talon Lama di Drago","num":3},{"id":91004,"name":"Talon SSW","num":4},{"id":91005,"name":"Talon Luna di Sangue","num":5}]},"Gangplank":{"id":41,"key":"Gangplank","name":"Gangplank","title":"il flagello dei mari","skins":[{"id":41000,"name":"default","num":0},{"id":41001,"name":"Gangplank Spettrale","num":1},{"id":41002,"name":"Gangplank Milizia","num":2},{"id":41003,"name":"Gangplank Marinaio","num":3},{"id":41004,"name":"Gangplank Soldatino Giocattolo","num":4},{"id":41005,"name":"Gangplank Forze Speciali","num":5},{"id":41006,"name":"Gangplank Sultano","num":6},{"id":41007,"name":"Capitano Gangplank","num":7},{"id":41008,"name":"Gangplank Nova del Terrore","num":8}]},"Ezreal":{"id":81,"key":"Ezreal","name":"Ezreal","title":"il prodigo esploratore","skins":[{"id":81000,"name":"default","num":0},{"id":81001,"name":"Ezreal da Nottingham","num":1},{"id":81002,"name":"Ezreal Attaccante","num":2},{"id":81003,"name":"Ezreal dei Ghiacci","num":3},{"id":81004,"name":"Ezreal Esploratore","num":4},{"id":81005,"name":"Ezreal Pulsefire","num":5},{"id":81006,"name":"TPA Ezreal","num":6},{"id":81007,"name":"Ezreal Rubacuori","num":7},{"id":81008,"name":"Ezreal Asso di Picche","num":8},{"id":81009,"name":"Ezreal Arcade","num":9},{"id":81018,"name":"Ezreal Guardiano Stellare","num":18}]},"Gnar":{"id":150,"key":"Gnar","name":"Gnar","title":"l'anello mancante","skins":[{"id":150000,"name":"default","num":0},{"id":150001,"name":"Gnarsauro","num":1},{"id":150002,"name":"Gnar Gentiluomo","num":2},{"id":150003,"name":"Gnar della Nevicata","num":3},{"id":150004,"name":"Gnar El León","num":4},{"id":150013,"name":"Gnar Megagalattico","num":13}]},"Teemo":{"id":17,"key":"Teemo","name":"Teemo","title":"il rapido scout","skins":[{"id":17000,"name":"default","num":0},{"id":17001,"name":"Teemo Elfo Felice","num":1},{"id":17002,"name":"Teemo Ricognitore","num":2},{"id":17003,"name":"Teemo Tasso","num":3},{"id":17004,"name":"Teemo Astronauta","num":4},{"id":17005,"name":"Teemo Coda a Batuffoli","num":5},{"id":17006,"name":"Super Teemo","num":6},{"id":17007,"name":"Teemo Panda","num":7},{"id":17008,"name":"Teemo Squadra Omega","num":8},{"id":17014,"name":"Teemo Diavoletto","num":14}]},"Annie":{"id":1,"key":"Annie","name":"Annie","title":"la bambina oscura","skins":[{"id":1000,"name":"default","num":0},{"id":1001,"name":"Annie Goth","num":1},{"id":1002,"name":"Cappuccetto Annie","num":2},{"id":1003,"name":"Annie nel Paese delle Meraviglie","num":3},{"id":1004,"name":"Annie Reginetta del Ballo","num":4},{"id":1005,"name":"Annie Ghiaccio Ardente","num":5},{"id":1006,"name":"Annie al Contrario","num":6},{"id":1007,"name":"Annie Frankentibbers","num":7},{"id":1008,"name":"Annie Panda","num":8},{"id":1009,"name":"Annie del Cuore","num":9},{"id":1010,"name":"Annie Hextech","num":10},{"id":1011,"name":"Annie Megagalattica","num":11}]},"Mordekaiser":{"id":82,"key":"Mordekaiser","name":"Mordekaiser","title":"il revenant di ferro","skins":[{"id":82000,"name":"default","num":0},{"id":82001,"name":"Mordekaiser Cavaliere del Drago","num":1},{"id":82002,"name":"Mordekaiser Infernale","num":2},{"id":82003,"name":"Mordekaiser dei Pentakill","num":3},{"id":82004,"name":"Lord Mordekaiser","num":4},{"id":82005,"name":"Mordekaiser Re di Fiori","num":5}]},"Azir":{"id":268,"key":"Azir","name":"Azir","title":"l'imperatore delle sabbie","skins":[{"id":268000,"name":"default","num":0},{"id":268001,"name":"Azir Galattico","num":1},{"id":268002,"name":"Azir Signore delle tombe","num":2},{"id":268003,"name":"Azir SKT T1","num":3},{"id":268004,"name":"Azir dei Regni in Guerra","num":4}]},"Kennen":{"id":85,"key":"Kennen","name":"Kennen","title":"il cuore della tempesta","skins":[{"id":85000,"name":"default","num":0},{"id":85001,"name":"Kennen Mortale","num":1},{"id":85002,"name":"Kennen Signore della Palude","num":2},{"id":85003,"name":"Karate Kennen","num":3},{"id":85004,"name":"Dottor Kennen","num":4},{"id":85005,"name":"Kennen Operazioni Artiche","num":5},{"id":85006,"name":"Kennen Luna di Sangue","num":6},{"id":85007,"name":"Super Kennen","num":7}]},"Riven":{"id":92,"key":"Riven","name":"Riven","title":"l'esiliata","skins":[{"id":92000,"name":"default","num":0},{"id":92001,"name":"Riven Redenta","num":1},{"id":92002,"name":"Riven dell'Élite Cremisi","num":2},{"id":92003,"name":"Riven Coniglietta da Battaglia","num":3},{"id":92004,"name":"Riven Stagione 2012","num":4},{"id":92005,"name":"Riven Lama di Drago","num":5},{"id":92006,"name":"Riven Arcade","num":6},{"id":92007,"name":"Riven Stagione 2016","num":7},{"id":92016,"name":"Riven Portatrice dell'Alba","num":16}]},"Chogath":{"id":31,"key":"Chogath","name":"Cho'Gath","title":"il terrore del Vuoto","skins":[{"id":31000,"name":"default","num":0},{"id":31001,"name":"Cho'Gath Incubo","num":1},{"id":31002,"name":"Cho'Gath Gentiluomo","num":2},{"id":31003,"name":"Cho'Gath Loch Ness","num":3},{"id":31004,"name":"Cho'Gath Giurassico","num":4},{"id":31005,"name":"Cho'Gath Macchina da Guerra","num":5},{"id":31006,"name":"Cho'Gath Preistorico","num":6}]},"Aatrox":{"id":266,"key":"Aatrox","name":"Aatrox","title":"la lama dei Darkin","skins":[{"id":266000,"name":"default","num":0},{"id":266001,"name":"Aatrox Giustiziere","num":1},{"id":266002,"name":"Mecha Aatrox","num":2},{"id":266003,"name":"Aatrox Cacciatore dei Mari","num":3}]},"Poppy":{"id":78,"key":"Poppy","name":"Poppy","title":"la custode del martello","skins":[{"id":78000,"name":"default","num":0},{"id":78001,"name":"Poppy di Noxus","num":1},{"id":78002,"name":"Lollipoppy","num":2},{"id":78003,"name":"Poppy Fabbro","num":3},{"id":78004,"name":"Poppy Bambola di Pezza","num":4},{"id":78005,"name":"Poppy Paramenti da Battaglia","num":5},{"id":78006,"name":"Poppy Martello Scarlatto","num":6},{"id":78007,"name":"Poppy Guardiana Stellare","num":7}]},"Taliyah":{"id":163,"key":"Taliyah","name":"Taliyah","title":"la tessitrice di pietre","skins":[{"id":163000,"name":"default","num":0},{"id":163001,"name":"Taliyah del Freljord","num":1}]},"Illaoi":{"id":420,"key":"Illaoi","name":"Illaoi","title":"la sacerdotessa del kraken","skins":[{"id":420000,"name":"default","num":0},{"id":420001,"name":"Illaoi Portatrice del Vuoto","num":1}]},"Heimerdinger":{"id":74,"key":"Heimerdinger","name":"Heimerdinger","title":"il riverito inventore","skins":[{"id":74000,"name":"default","num":0},{"id":74001,"name":"Heimerdinger Invasore Alieno","num":1},{"id":74002,"name":"Heimerdinger Esperimento Fallito","num":2},{"id":74003,"name":"Heimy Meccanico di Piltover","num":3},{"id":74004,"name":"Neverdinger","num":4},{"id":74005,"name":"Heimerdinger Nucleare","num":5}]},"Alistar":{"id":12,"key":"Alistar","name":"Alistar","title":"il minotauro","skins":[{"id":12000,"name":"default","num":0},{"id":12001,"name":"Alistar Nero","num":1},{"id":12002,"name":"Alistar d'Oro","num":2},{"id":12003,"name":"Alistar Matador","num":3},{"id":12004,"name":"Alistar Corna Lunghe","num":4},{"id":12005,"name":"Alistar Scatenato","num":5},{"id":12006,"name":"Alistar Infernale","num":6},{"id":12007,"name":"Alistar Libero Insuperabile","num":7},{"id":12008,"name":"Alistar Predone","num":8},{"id":12009,"name":"Alistar SKT T1","num":9},{"id":12010,"name":"Alistar Mucca Muu","num":10}]},"XinZhao":{"id":5,"key":"XinZhao","name":"Xin Zhao","title":"il siniscalco di Demacia","skins":[{"id":5000,"name":"default","num":0},{"id":5001,"name":"Xin Zhao Commando","num":1},{"id":5002,"name":"Xin Zhao Imperiale","num":2},{"id":5003,"name":"Xin Zhao Viscero","num":3},{"id":5004,"name":"Xin Zhao Ussaro Alato","num":4},{"id":5005,"name":"Xin Zhao dei Regni in Guerra","num":5},{"id":5006,"name":"Xin Zhao Agente Segreto","num":6},{"id":5013,"name":"Xin Zhao Ammazzadraghi","num":13}]},"Lucian":{"id":236,"key":"Lucian","name":"Lucian","title":"il purificatore","skins":[{"id":236000,"name":"default","num":0},{"id":236001,"name":"Lucian Mercenario","num":1},{"id":236002,"name":"Lucian Cannoniere","num":2},{"id":236006,"name":"PROGETTO: Lucian","num":6},{"id":236007,"name":"Lucian Cerca Cuori","num":7}]},"Volibear":{"id":106,"key":"Volibear","name":"Volibear","title":"il ruggito del tuono","skins":[{"id":106000,"name":"default","num":0},{"id":106001,"name":"Volibear Signore del Tuono","num":1},{"id":106002,"name":"Volibear Tempesta del Nord","num":2},{"id":106003,"name":"Volibear Guardia Runica","num":3},{"id":106004,"name":"Capitano Volibear","num":4},{"id":106005,"name":"Volibear El Rayo","num":5}]},"Sejuani":{"id":113,"key":"Sejuani","name":"Sejuani","title":"Furia del nord","skins":[{"id":113000,"name":"default","num":0},{"id":113001,"name":"Sejuani della Foresta","num":1},{"id":113002,"name":"Sejuani Cavaliere Oscuro","num":2},{"id":113003,"name":"Sejuani Tradizionale","num":3},{"id":113004,"name":"Sejuani Cavaliere dell'Orso","num":4},{"id":113005,"name":"Sejuani Cavalcaporo","num":5},{"id":113006,"name":"Sejuani Cacciatrice di Bestie","num":6},{"id":113007,"name":"Sejuani Cacciatrice d'Albe","num":7}]},"Nidalee":{"id":76,"key":"Nidalee","name":"Nidalee","title":"la cacciatrice bestiale","skins":[{"id":76000,"name":"default","num":0},{"id":76001,"name":"Nidalee delle Nevi","num":1},{"id":76002,"name":"Nidalee Leopardata","num":2},{"id":76003,"name":"Nidalee Cameriera","num":3},{"id":76004,"name":"Faraona Nidalee","num":4},{"id":76005,"name":"Nidalee Stregatta","num":5},{"id":76006,"name":"Nidalee Cacciatrice di Teste","num":6},{"id":76007,"name":"Nidalee dei Regni in Guerra","num":7},{"id":76008,"name":"Nidalee Impavida","num":8},{"id":76009,"name":"Nidalee Megagalattica","num":9}]},"Garen":{"id":86,"key":"Garen","name":"Garen","title":"la potenza di Demacia","skins":[{"id":86000,"name":"default","num":0},{"id":86001,"name":"Garen Sanguinario","num":1},{"id":86002,"name":"Garen Truppa del Deserto","num":2},{"id":86003,"name":"Garen Commando","num":3},{"id":86004,"name":"Garen Cavaliere Oscuro","num":4},{"id":86005,"name":"Garen Veterano","num":5},{"id":86006,"name":"Garen Legione d'Acciaio","num":6},{"id":86010,"name":"Garen Ammiraglio Corsaro","num":10},{"id":86011,"name":"Garen dei Regni in Guerra","num":11}]},"Leona":{"id":89,"key":"Leona","name":"Leona","title":"l'alba raggiante","skins":[{"id":89000,"name":"default","num":0},{"id":89001,"name":"Leona Valchiria ","num":1},{"id":89002,"name":"Leona Paladina","num":2},{"id":89003,"name":"Leona dei Solari di Ferro","num":3},{"id":89004,"name":"Leona Festa in Piscina","num":4},{"id":89008,"name":"PROGETTO: Leona","num":8},{"id":89009,"name":"Leona Barbecue","num":9}]},"Zed":{"id":238,"key":"Zed","name":"Zed","title":"il maestro delle ombre","skins":[{"id":238000,"name":"default","num":0},{"id":238001,"name":"Zed Elettrolama","num":1},{"id":238002,"name":"Zed SKT T1","num":2},{"id":238003,"name":"PROGETTO: Zed","num":3},{"id":238010,"name":"Zed Stagione 2016","num":10},{"id":238011,"name":"Zed Adepto della Morte","num":11}]},"Blitzcrank":{"id":53,"key":"Blitzcrank","name":"Blitzcrank","title":"il grande golem a vapore","skins":[{"id":53000,"name":"default","num":0},{"id":53001,"name":"Blitzcrank Arrugginito","num":1},{"id":53002,"name":"Blitzcrank Portiere","num":2},{"id":53003,"name":"Blitzcrank Boom Boom","num":3},{"id":53004,"name":"Blitzcrank Truccato a Piltover","num":4},{"id":53005,"name":"Sicuramente non Blitzcrank","num":5},{"id":53006,"name":"iBlitzcrank","num":6},{"id":53007,"name":"Riot Blitzcrank ","num":7},{"id":53011,"name":"Blitzcrank Boss da Battaglia","num":11},{"id":53020,"name":"Blitzcrank Lanciere Solitario","num":20},{"id":53021,"name":"Blitzcrank Lanciere Eroico","num":21}]},"Rammus":{"id":33,"key":"Rammus","name":"Rammus","title":"l'arma-dillo","skins":[{"id":33000,"name":"default","num":0},{"id":33001,"name":"Re Rammus","num":1},{"id":33002,"name":"Rammus Cromato","num":2},{"id":33003,"name":"Rammus Fuso","num":3},{"id":33004,"name":"Rammus del Freljord","num":4},{"id":33005,"name":"Rammus Ninja","num":5},{"id":33006,"name":"Full Metal Rammus","num":6},{"id":33007,"name":"Rammus Guardiano delle Sabbie","num":7}]},"Velkoz":{"id":161,"key":"Velkoz","name":"Vel'Koz","title":"l'occhio del Vuoto","skins":[{"id":161000,"name":"default","num":0},{"id":161001,"name":"Vel'Koz Macchina da Guerra","num":1},{"id":161002,"name":"Vel'Koz della Luce","num":2},{"id":161003,"name":"Sicuramente non Vel'Koz","num":3}]},"Caitlyn":{"id":51,"key":"Caitlyn","name":"Caitlyn","title":"lo sceriffo di Piltover","skins":[{"id":51000,"name":"default","num":0},{"id":51001,"name":"Caitlyn della Resistenza","num":1},{"id":51002,"name":"Sceriffo Caitlyn","num":2},{"id":51003,"name":"Caitlyn da Safari","num":3},{"id":51004,"name":"Caitlyn Guerra Artica","num":4},{"id":51005,"name":"Agente Caitlyn","num":5},{"id":51006,"name":"Caitlyn Cacciatrice di Teste","num":6},{"id":51010,"name":"Caitlyn Spettro Lunare","num":10},{"id":51011,"name":"Caitlyn Pulsefire","num":11}]},"Trundle":{"id":48,"key":"Trundle","name":"Trundle","title":"il re dei troll","skins":[{"id":48000,"name":"default","num":0},{"id":48001,"name":"Trundle Battitore","num":1},{"id":48002,"name":"Trundle da Discarica","num":2},{"id":48003,"name":"Trundle Tradizionale","num":3},{"id":48004,"name":"Commissario Trundle","num":4},{"id":48005,"name":"Trundle Distruttore del mondo","num":5}]},"Kindred":{"id":203,"key":"Kindred","name":"Kindred","title":"i cacciatori eterni","skins":[{"id":203000,"name":"default","num":0},{"id":203001,"name":"Kindred Ombra di Fuoco","num":1},{"id":203002,"name":"Kindred Megagalattico","num":2}]},"Quinn":{"id":133,"key":"Quinn","name":"Quinn","title":"le ali di Demacia","skins":[{"id":133000,"name":"default","num":0},{"id":133001,"name":"Quinn Fenice","num":1},{"id":133002,"name":"Quinn Esploratrice Guerriera","num":2},{"id":133003,"name":"Quinn Corsara","num":3},{"id":133004,"name":"Quinn Cerca Cuori","num":4}]},"Ekko":{"id":245,"key":"Ekko","name":"Ekko","title":"il ragazzo che ha infranto il tempo","skins":[{"id":245000,"name":"default","num":0},{"id":245001,"name":"Ekko Tempesta di Sabbia","num":1},{"id":245002,"name":"Ekko dell'Accademia","num":2},{"id":245003,"name":"PROGETTO: Ekko","num":3},{"id":245011,"name":"Ekko SKT T1","num":11}]},"Nami":{"id":267,"key":"Nami","name":"Nami","title":"lo spirito delle maree","skins":[{"id":267000,"name":"default","num":0},{"id":267001,"name":"Nami Koi","num":1},{"id":267002,"name":"Nami Spirito del Fiume","num":2},{"id":267003,"name":"Urf il Namintino","num":3},{"id":267007,"name":"Nami delle Profondità","num":7},{"id":267008,"name":"Nami SKT T1","num":8}]},"Swain":{"id":50,"key":"Swain","name":"Swain","title":"il grande stratega","skins":[{"id":50000,"name":"default","num":0},{"id":50001,"name":"Swain del Fronte del Nord","num":1},{"id":50002,"name":"Swain di Bilgewater","num":2},{"id":50003,"name":"Swain Tiranno","num":3}]},"Taric":{"id":44,"key":"Taric","name":"Taric","title":"lo scudo di Valoran","skins":[{"id":44000,"name":"default","num":0},{"id":44001,"name":"Taric Smeraldo","num":1},{"id":44002,"name":"Taric Armatura della Quinta Era","num":2},{"id":44003,"name":"Taric Pietra Sanguigna","num":3},{"id":44004,"name":"Taric Festa in Piscina","num":4}]},"Syndra":{"id":134,"key":"Syndra","name":"Syndra","title":"la sovrana dell'oscurità","skins":[{"id":134000,"name":"default","num":0},{"id":134001,"name":"Syndra Grande Giustiziera","num":1},{"id":134002,"name":"Syndra Atlantidea","num":2},{"id":134003,"name":"Syndra Regina di Quadri","num":3},{"id":134004,"name":"Syndra della Nevicata","num":4},{"id":134005,"name":"Syndra SKT T1","num":5},{"id":134006,"name":"Syndra Guardiana Stellare","num":6}]},"Rakan":{"id":497,"key":"Rakan","name":"Rakan","title":"l'ammaliatore","skins":[{"id":497000,"name":"default","num":0},{"id":497001,"name":"Rakan Alba Cosmica","num":1}]},"Skarner":{"id":72,"key":"Skarner","name":"Skarner","title":"l'avanguardia di cristallo","skins":[{"id":72000,"name":"default","num":0},{"id":72001,"name":"Skarner Flagello delle Sabbie","num":1},{"id":72002,"name":"Skarner Terra Runica","num":2},{"id":72003,"name":"Skarner Macchina da Guerra Alpha","num":3},{"id":72004,"name":"Skarner Guardiano delle Sabbie","num":4}]},"Braum":{"id":201,"key":"Braum","name":"Braum","title":"il cuore del Freljord","skins":[{"id":201000,"name":"default","num":0},{"id":201001,"name":"Braum Ammazzadraghi","num":1},{"id":201002,"name":"Braum El Tigre","num":2},{"id":201003,"name":"Braum Cuordileone","num":3},{"id":201010,"name":"Babbo Braum","num":10}]},"Veigar":{"id":45,"key":"Veigar","name":"Veigar","title":"il piccolo genio del male","skins":[{"id":45000,"name":"default","num":0},{"id":45001,"name":"Veigar Mago Bianco","num":1},{"id":45002,"name":"Veigar Mago del Curling","num":2},{"id":45003,"name":"Veigar il Grigio","num":3},{"id":45004,"name":"Veigar Folletto","num":4},{"id":45005,"name":"Barone Von Veigar","num":5},{"id":45006,"name":"Cattivissimo Veigar","num":6},{"id":45007,"name":"Veigar Babbo Letale","num":7},{"id":45008,"name":"Veigar Boss Finale","num":8},{"id":45009,"name":"Veigar Squadra Omega","num":9}]},"Xerath":{"id":101,"key":"Xerath","name":"Xerath","title":"il magus ascendente","skins":[{"id":101000,"name":"default","num":0},{"id":101001,"name":"Xerath Figlio delle Rune","num":1},{"id":101002,"name":"Xerath Macchina da Guerra","num":2},{"id":101003,"name":"Xerath Terra Bruciata","num":3},{"id":101004,"name":"Xerath Guardiano delle Sabbie","num":4}]},"Corki":{"id":42,"key":"Corki","name":"Corki","title":"il bombardiere spericolato","skins":[{"id":42000,"name":"default","num":0},{"id":42001,"name":"Corki UFO","num":1},{"id":42002,"name":"Corki Slitta da Neve","num":2},{"id":42003,"name":"Corki Barone Rosso","num":3},{"id":42004,"name":"Corki Hot Rod","num":4},{"id":42005,"name":"Corki Cavalca-Urf","num":5},{"id":42006,"name":"Corki Ala di Drago","num":6},{"id":42007,"name":"Corki Fnatic","num":7},{"id":42008,"name":"Corki Arcade","num":8}]},"Nautilus":{"id":111,"key":"Nautilus","name":"Nautilus","title":"il titano delle profondità","skins":[{"id":111000,"name":"default","num":0},{"id":111001,"name":"Nautilus Abissale","num":1},{"id":111002,"name":"Nautilus Sotterraneo","num":2},{"id":111003,"name":"Astronautilus","num":3},{"id":111004,"name":"Nautilus Inquisitore","num":4},{"id":111005,"name":"Nautilus Distruttore del mondo","num":5}]},"Ahri":{"id":103,"key":"Ahri","name":"Ahri","title":"la volpe a nove code","skins":[{"id":103000,"name":"default","num":0},{"id":103001,"name":"Ahri della Dinastia","num":1},{"id":103002,"name":"Ahri di Mezzanotte","num":2},{"id":103003,"name":"Ahri Volpe di Fuoco","num":3},{"id":103004,"name":"Ahri Popstar","num":4},{"id":103005,"name":"Ahri Impavida","num":5},{"id":103006,"name":"Ahri dell'Accademia","num":6},{"id":103007,"name":"Ahri Arcade","num":7},{"id":103014,"name":"Ahri Guardiana Stellare","num":14}]},"Jayce":{"id":126,"key":"Jayce","name":"Jayce","title":"il difensore del domani","skins":[{"id":126000,"name":"default","num":0},{"id":126001,"name":"Full Metal Jayce","num":1},{"id":126002,"name":"Jayce Rubacuori ","num":2},{"id":126003,"name":"Jayce il Reietto","num":3},{"id":126004,"name":"Jayce Martello Lucente","num":4}]},"Darius":{"id":122,"key":"Darius","name":"Darius","title":"la mano di Noxus","skins":[{"id":122000,"name":"default","num":0},{"id":122001,"name":"Lord Darius","num":1},{"id":122002,"name":"Darius della Bioforgia","num":2},{"id":122003,"name":"Darius Pittura di Guerra","num":3},{"id":122004,"name":"Darius Maestro delle Schiacciate","num":4},{"id":122008,"name":"Darius dell'Accademia","num":8},{"id":122014,"name":"Darius Nova del Terrore","num":14}]},"Tryndamere":{"id":23,"key":"Tryndamere","name":"Tryndamere","title":"il re barbaro","skins":[{"id":23000,"name":"default","num":0},{"id":23001,"name":"Tryndamere delle Highland","num":1},{"id":23002,"name":"Re Tryndamere","num":2},{"id":23003,"name":"Tryndamere Vichingo","num":3},{"id":23004,"name":"Tryndamere Lama Demoniaca","num":4},{"id":23005,"name":"Tryndamere Sultano","num":5},{"id":23006,"name":"Tryndamere dei Regni in Guerra","num":6},{"id":23007,"name":"Tryndamere Incubo","num":7},{"id":23008,"name":"Tryndamere Cacciatore di Bestie","num":8},{"id":23009,"name":"Tryndamere Chemtech","num":9}]},"Janna":{"id":40,"key":"Janna","name":"Janna","title":"la furia della tempesta","skins":[{"id":40000,"name":"default","num":0},{"id":40001,"name":"Janna della Tempesta","num":1},{"id":40002,"name":"Janna Hextech","num":2},{"id":40003,"name":"Janna Regina dei Ghiacci","num":3},{"id":40004,"name":"Janna Vittoriosa","num":4},{"id":40005,"name":"Janna Meteorina","num":5},{"id":40006,"name":"Janna Fnatic","num":6},{"id":40007,"name":"Janna Guardiana Stellare","num":7},{"id":40008,"name":"Janna Spada Sacra","num":8}]},"Elise":{"id":60,"key":"Elise","name":"Elise","title":"la regina dei ragni","skins":[{"id":60000,"name":"default","num":0},{"id":60001,"name":"Elise Bocciolo Mortale","num":1},{"id":60002,"name":"Elise Vittoriosa","num":2},{"id":60003,"name":"Elise Luna di Sangue","num":3},{"id":60004,"name":"Elise SKT T1","num":4},{"id":60005,"name":"Elise Megagalattica","num":5}]},"Vayne":{"id":67,"key":"Vayne","name":"Vayne","title":"la cacciatrice notturna","skins":[{"id":67000,"name":"default","num":0},{"id":67001,"name":"Vayne Vendicatrice","num":1},{"id":67002,"name":"Vayne Aristocratica","num":2},{"id":67003,"name":"Vayne Ammazzadraghi","num":3},{"id":67004,"name":"Vayne Cerca Cuori","num":4},{"id":67005,"name":"Vayne SKT T1","num":5},{"id":67006,"name":"Vayne della Luce","num":6},{"id":67010,"name":"Vayne Ladra d'anime","num":10}]},"Brand":{"id":63,"key":"Brand","name":"Brand","title":"la vendetta ardente","skins":[{"id":63000,"name":"default","num":0},{"id":63001,"name":"Brand Apocalittico","num":1},{"id":63002,"name":"Brand Vandalo","num":2},{"id":63003,"name":"Brand Crio-nucleo","num":3},{"id":63004,"name":"Brand Zombi","num":4},{"id":63005,"name":"Brand Fuoco Spirituale","num":5},{"id":63006,"name":"Brand Boss da Battaglia","num":6}]},"Graves":{"id":104,"key":"Graves","name":"Graves","title":"il fuorilegge","skins":[{"id":104000,"name":"default","num":0},{"id":104001,"name":"Graves Mercenario","num":1},{"id":104002,"name":"Graves Evaso","num":2},{"id":104003,"name":"Graves Mafioso","num":3},{"id":104004,"name":"Riot Graves","num":4},{"id":104005,"name":"Graves Festa in Piscina","num":5},{"id":104006,"name":"Graves Tagliagole","num":6},{"id":104007,"name":"Graves della Nevicata","num":7},{"id":104014,"name":"Graves Vittorioso","num":14}]},"Soraka":{"id":16,"key":"Soraka","name":"Soraka","title":"la figlia delle stelle","skins":[{"id":16000,"name":"default","num":0},{"id":16001,"name":"Soraka Driade","num":1},{"id":16002,"name":"Soraka la Divina","num":2},{"id":16003,"name":"Soraka Celestina","num":3},{"id":16004,"name":"Soraka Mietitrice","num":4},{"id":16005,"name":"Soraka Ordine della Banana","num":5},{"id":16006,"name":"Programma Soraka","num":6},{"id":16007,"name":"Soraka Guardiana Stellare","num":7}]},"Xayah":{"id":498,"key":"Xayah","name":"Xayah","title":"la ribelle","skins":[{"id":498000,"name":"default","num":0},{"id":498001,"name":"Xayah Crepuscolo Cosmico","num":1}]},"Karthus":{"id":30,"key":"Karthus","name":"Karthus","title":"il cantore della morte","skins":[{"id":30000,"name":"default","num":0},{"id":30001,"name":"Karthus Fantasma","num":1},{"id":30002,"name":"Statua di Karthus","num":2},{"id":30003,"name":"Karthus Tristo Mietitore","num":3},{"id":30004,"name":"Karthus dei Pentakill","num":4},{"id":30005,"name":"Karthus Fnatic","num":5},{"id":30009,"name":"Karthus Rovina della Luce","num":9}]},"Vladimir":{"id":8,"key":"Vladimir","name":"Vladimir","title":"il mietitore cremisi","skins":[{"id":8000,"name":"default","num":0},{"id":8001,"name":"Conte Vladimir","num":1},{"id":8002,"name":"Marchese Vladimir","num":2},{"id":8003,"name":"Vladimir Nosferatu","num":3},{"id":8004,"name":"Vladimir Vandalo","num":4},{"id":8005,"name":"Vladimir Signore del Sangue","num":5},{"id":8006,"name":"Vladimir Ladro d'Anime","num":6},{"id":8007,"name":"Vladimir dell'Accademia","num":7}]},"Zilean":{"id":26,"key":"Zilean","name":"Zilean","title":"il custode del tempo","skins":[{"id":26000,"name":"default","num":0},{"id":26001,"name":"Zilean Vecchio Santo","num":1},{"id":26002,"name":"Zilean Fricchettone","num":2},{"id":26003,"name":"Zilean del Deserto di Shurima","num":3},{"id":26004,"name":"Zilean Macchina del Tempo","num":4},{"id":26005,"name":"Zilean Luna di Sangue","num":5}]},"Katarina":{"id":55,"key":"Katarina","name":"Katarina","title":"la lama sinistra","skins":[{"id":55000,"name":"default","num":0},{"id":55001,"name":"Katarina Mercenaria","num":1},{"id":55002,"name":"Katarina Arbitro","num":2},{"id":55003,"name":"Katarina di Bilgewater","num":3},{"id":55004,"name":"Katarina Micio Miao","num":4},{"id":55005,"name":"Katarina dell'Alto Comando","num":5},{"id":55006,"name":"Katarina Tempesta di Sabbia","num":6},{"id":55007,"name":"Katarina Renna","num":7},{"id":55008,"name":"Katarina dei Regni in Guerra","num":8},{"id":55009,"name":"PROGETTO: Katarina","num":9},{"id":55010,"name":"Katarina Adepta della Morte","num":10}]},"Shyvana":{"id":102,"key":"Shyvana","name":"Shyvana","title":"il mezzo-drago","skins":[{"id":102000,"name":"default","num":0},{"id":102001,"name":"Shyvana Scaglie di Ferro","num":1},{"id":102002,"name":"Shyvana Zanne d'Ossa","num":2},{"id":102003,"name":"Shyvana Fiamma Oscura","num":3},{"id":102004,"name":"Shyvana Drago di Ghiaccio","num":4},{"id":102005,"name":"Shyvana Stagione 2014","num":5},{"id":102006,"name":"Shyvana Megagalattica","num":6}]},"Warwick":{"id":19,"key":"Warwick","name":"Warwick","title":"la furia scatenata di Zaun","skins":[{"id":19000,"name":"default","num":0},{"id":19001,"name":"Warwick Grigio","num":1},{"id":19002,"name":"Urf il Lamantino","num":2},{"id":19003,"name":"Grosso Warwick Cattivo","num":3},{"id":19004,"name":"Warwick Cacciatore della Tundra","num":4},{"id":19005,"name":"Warwick Ferale","num":5},{"id":19006,"name":"Warwick Zanna di Fuoco","num":6},{"id":19007,"name":"Warwick Iena","num":7},{"id":19008,"name":"Warwick Predone","num":8},{"id":19009,"name":"Urfwick","num":9}]},"Ziggs":{"id":115,"key":"Ziggs","name":"Ziggs","title":"l'esperto di hexplosivi","skins":[{"id":115000,"name":"default","num":0},{"id":115001,"name":"Ziggs Scienziato Pazzo","num":1},{"id":115002,"name":"Maggiore Ziggs","num":2},{"id":115003,"name":"Ziggs Festa in Piscina","num":3},{"id":115004,"name":"Ziggs della Nevicata","num":4},{"id":115005,"name":"Ziggs Maestro dell'Arcano","num":5},{"id":115006,"name":"Ziggs Boss da Battaglia","num":6}]},"Kled":{"id":240,"key":"Kled","name":"Kled","title":"l'isterico cavaliere","skins":[{"id":240000,"name":"default","num":0},{"id":240001,"name":"Sir Kled","num":1}]},"Khazix":{"id":121,"key":"Khazix","name":"Kha'Zix","title":"il razziatore del Vuoto","skins":[{"id":121000,"name":"default","num":0},{"id":121001,"name":"Mecha Kha'Zix","num":1},{"id":121002,"name":"Kha'Zix Guardiano delle Sabbie","num":2},{"id":121003,"name":"Kha'Zix Bocciolo Mortale","num":3},{"id":121004,"name":"Kha'Zix Stella Oscura","num":4}]},"Olaf":{"id":2,"key":"Olaf","name":"Olaf","title":"il berserker","skins":[{"id":2000,"name":"default","num":0},{"id":2001,"name":"Olaf il Reietto","num":1},{"id":2002,"name":"Olaf il Glaciale","num":2},{"id":2003,"name":"Brolaf","num":3},{"id":2004,"name":"Olaf dei Pentakill","num":4},{"id":2005,"name":"Olaf Predone","num":5},{"id":2006,"name":"Olaf Macellaio","num":6},{"id":2015,"name":"Olaf SKT T1","num":15}]},"TwistedFate":{"id":4,"key":"TwistedFate","name":"Twisted Fate","title":"il maestro di carte","skins":[{"id":4000,"name":"default","num":0},{"id":4001,"name":"PAX Twisted Fate","num":1},{"id":4002,"name":"Twisted Fate Fante di Cuori","num":2},{"id":4003,"name":"Il Magnifico Twisted Fate","num":3},{"id":4004,"name":"Twisted Fate Tango","num":4},{"id":4005,"name":"Twisted Fate Mezzogiorno di Fuoco","num":5},{"id":4006,"name":"Twisted Fate Moschettiere","num":6},{"id":4007,"name":"Twisted Fate dell'Oltretomba","num":7},{"id":4008,"name":"Twisted Fate Arbitro","num":8},{"id":4009,"name":"Twisted Fate Tagliaborse","num":9},{"id":4010,"name":"Twisted Fate Luna di Sangue","num":10}]},"Nunu":{"id":20,"key":"Nunu","name":"Nunu","title":"il cavalca yeti","skins":[{"id":20000,"name":"default","num":0},{"id":20001,"name":"Nunu Sasquatch ","num":1},{"id":20002,"name":"Nunu Elfo di Natale","num":2},{"id":20003,"name":"Nunu Grunge","num":3},{"id":20004,"name":"Nunu-bot","num":4},{"id":20005,"name":"Nunu il Demolitore","num":5},{"id":20006,"name":"TPA Nunu","num":6},{"id":20007,"name":"Nunu Zombi","num":7}]},"Rengar":{"id":107,"key":"Rengar","name":"Rengar","title":"il cacciatore orgoglioso","skins":[{"id":107000,"name":"default","num":0},{"id":107001,"name":"Rengar Cacciatore di Teste","num":1},{"id":107002,"name":"Rengar Cacciatore Notturno","num":2},{"id":107003,"name":"Rengar SSW","num":3},{"id":107008,"name":"Mecha Rengar","num":8}]},"Bard":{"id":432,"key":"Bard","name":"Bard","title":"il custode errante","skins":[{"id":432000,"name":"default","num":0},{"id":432001,"name":"Bard del Bosco Antico","num":1},{"id":432005,"name":"Bard della Nevicata","num":5},{"id":432006,"name":"Bard Bardo","num":6}]},"Irelia":{"id":39,"key":"Irelia","name":"Irelia","title":"il volere delle lame","skins":[{"id":39000,"name":"default","num":0},{"id":39001,"name":"Irelia Lama della Notte","num":1},{"id":39002,"name":"Irelia Aviatrice","num":2},{"id":39003,"name":"Irelia Spia Infiltrata","num":3},{"id":39004,"name":"Irelia Gladio Ghiacciato","num":4},{"id":39005,"name":"Irelia Ordine del Loto","num":5}]},"Ivern":{"id":427,"key":"Ivern","name":"Ivern","title":"l'anziano della foresta","skins":[{"id":427000,"name":"default","num":0},{"id":427001,"name":"Ivern Re dei Dolci","num":1}]},"MonkeyKing":{"id":62,"key":"MonkeyKing","name":"Wukong","title":"il re delle scimmie","skins":[{"id":62000,"name":"default","num":0},{"id":62001,"name":"Wukong Vulcanico","num":1},{"id":62002,"name":"Wukong Generale","num":2},{"id":62003,"name":"Wukong Drago di Giada","num":3},{"id":62004,"name":"Wukong dell'Oltretomba","num":4},{"id":62005,"name":"Wukong Splendente","num":5}]},"Ashe":{"id":22,"key":"Ashe","name":"Ashe","title":"l'arciere dei ghiacci","skins":[{"id":22000,"name":"default","num":0},{"id":22001,"name":"Ashe del Freljord","num":1},{"id":22002,"name":"Ashe Foresta di Sherwood","num":2},{"id":22003,"name":"Ashe Pittura di Guerra","num":3},{"id":22004,"name":"Regina Ashe","num":4},{"id":22005,"name":"Ashe Ametista","num":5},{"id":22006,"name":"Ashe Cerca Cuori ","num":6},{"id":22007,"name":"Ashe Predona","num":7},{"id":22008,"name":"PROGETTO: Ashe","num":8},{"id":22009,"name":"Ashe Stagione 2017","num":9}]},"Kalista":{"id":429,"key":"Kalista","name":"Kalista","title":"la lancia della vendetta","skins":[{"id":429000,"name":"default","num":0},{"id":429001,"name":"Kalista Luna di Sangue","num":1},{"id":429002,"name":"Kalista Stagione 2015","num":2},{"id":429003,"name":"Kalista SKT T1","num":3}]},"Akali":{"id":84,"key":"Akali","name":"Akali","title":"il pugno dell'ombra","skins":[{"id":84000,"name":"default","num":0},{"id":84001,"name":"Akali Arpione","num":1},{"id":84002,"name":"Akali Cremisi","num":2},{"id":84003,"name":"Akali All-star","num":3},{"id":84004,"name":"Akali Infermiera","num":4},{"id":84005,"name":"Akali Luna di Sangue","num":5},{"id":84006,"name":"Akali Zanna d'Argento","num":6},{"id":84007,"name":"Akali Cacciatrice di Teste","num":7},{"id":84008,"name":"Akali Sashimi","num":8}]},"Vi":{"id":254,"key":"Vi","name":"Vi","title":"la legge di Piltover","skins":[{"id":254000,"name":"default","num":0},{"id":254001,"name":"Vi al Neon","num":1},{"id":254002,"name":"Agente Vi","num":2},{"id":254003,"name":"Vi Rubacuori","num":3},{"id":254004,"name":"Vi Demoniaca","num":4},{"id":254005,"name":"Vi dei Regni in Guerra","num":5}]},"Amumu":{"id":32,"key":"Amumu","name":"Amumu","title":"la mummia triste","skins":[{"id":32000,"name":"default","num":0},{"id":32001,"name":"Faraone Amumu","num":1},{"id":32002,"name":"Amumu Vancouver","num":2},{"id":32003,"name":"Emumu","num":3},{"id":32004,"name":"Amumu Regalo Riciclato","num":4},{"id":32005,"name":"Amumu Quasi-Re del Ballo","num":5},{"id":32006,"name":"Amumu Piccolo Cavaliere","num":6},{"id":32007,"name":"Amumu Triste Robot","num":7},{"id":32008,"name":"Amumu Festa a Sorpresa","num":8}]},"Lulu":{"id":117,"key":"Lulu","name":"Lulu","title":"la sacerdotessa delle fate","skins":[{"id":117000,"name":"default","num":0},{"id":117001,"name":"Lulu Dolceamara","num":1},{"id":117002,"name":"Lulu Crudele","num":2},{"id":117003,"name":"Lulu Addestratrice di Draghi","num":3},{"id":117004,"name":"Lulu Prodigio Invernale","num":4},{"id":117005,"name":"Lulu Festa in Piscina","num":5},{"id":117006,"name":"Lulu Guardiana Stellare","num":6}]},"Morgana":{"id":25,"key":"Morgana","name":"Morgana","title":"l'angelo caduto","skins":[{"id":25000,"name":"default","num":0},{"id":25001,"name":"Morgana Esiliata","num":1},{"id":25002,"name":"Morgana Golosità Peccaminosa","num":2},{"id":25003,"name":"Morgana Signora delle Lame","num":3},{"id":25004,"name":"Morgana Aculeo Nero","num":4},{"id":25005,"name":"Morgana Sposa Spettrale","num":5},{"id":25006,"name":"Morgana Vittoriosa","num":6},{"id":25010,"name":"Morgana Spettro Lunare","num":10},{"id":25011,"name":"Strega Morgana","num":11}]},"Nocturne":{"id":56,"key":"Nocturne","name":"Nocturne","title":"l'eterno incubo","skins":[{"id":56000,"name":"default","num":0},{"id":56001,"name":"Nocturne Terrore Gelido","num":1},{"id":56002,"name":"Nocturne del Vuoto","num":2},{"id":56003,"name":"Nocturne Razziatore","num":3},{"id":56004,"name":"Nocturne Infestato","num":4},{"id":56005,"name":"Nocturne Eternum","num":5},{"id":56006,"name":"Nocturne Revenant maledetto","num":6}]},"Diana":{"id":131,"key":"Diana","name":"Diana","title":"il disprezzo della Luna","skins":[{"id":131000,"name":"default","num":0},{"id":131001,"name":"Diana Valchiria Oscura","num":1},{"id":131002,"name":"Diana Dea Lunare","num":2},{"id":131003,"name":"Diana Infernale","num":3},{"id":131011,"name":"Diana Luna di Sangue","num":11}]},"AurelionSol":{"id":136,"key":"AurelionSol","name":"Aurelion Sol","title":"il forgiatore di stelle","skins":[{"id":136000,"name":"default","num":0},{"id":136001,"name":"Aurelion Sol Signore Cinereo","num":1}]},"Zyra":{"id":143,"key":"Zyra","name":"Zyra","title":"La dama dei rovi","skins":[{"id":143000,"name":"default","num":0},{"id":143001,"name":"Zyra dai Fiori Ardenti","num":1},{"id":143002,"name":"Zyra Infestata","num":2},{"id":143003,"name":"Zyra SKT T1","num":3},{"id":143004,"name":"Zyra Incantadraghi","num":4}]},"Viktor":{"id":112,"key":"Viktor","name":"Viktor","title":"l'araldo delle macchine","skins":[{"id":112000,"name":"default","num":0},{"id":112001,"name":"Viktor Macchina Completa","num":1},{"id":112002,"name":"Viktor Prototipo","num":2},{"id":112003,"name":"Viktor Creatore","num":3},{"id":112004,"name":"Viktor Adepto della Morte","num":4}]},"Cassiopeia":{"id":69,"key":"Cassiopeia","name":"Cassiopeia","title":"l'abbraccio del serpente","skins":[{"id":69000,"name":"default","num":0},{"id":69001,"name":"Cassiopeia Desperada","num":1},{"id":69002,"name":"Cassiopeia Sirena","num":2},{"id":69003,"name":"Cassiopeia Mitologica","num":3},{"id":69004,"name":"Cassiopeia Zanna di Giada","num":4},{"id":69008,"name":"Cassiopeia Eternum","num":8}]},"Nasus":{"id":75,"key":"Nasus","name":"Nasus","title":"il custode delle dune","skins":[{"id":75000,"name":"default","num":0},{"id":75001,"name":"Nasus Galattico","num":1},{"id":75002,"name":"Faraone Nasus","num":2},{"id":75003,"name":"Nasus Cavaliere Oscuro","num":3},{"id":75004,"name":"Riot K-9 Nasus","num":4},{"id":75005,"name":"Nasus Infernale","num":5},{"id":75006,"name":"Duca Conte Nasus","num":6},{"id":75010,"name":"Nasus Distruttore del mondo","num":10}]},"Twitch":{"id":29,"key":"Twitch","name":"Twitch","title":"il ratto della peste","skins":[{"id":29000,"name":"default","num":0},{"id":29001,"name":"Twitch Re del Crimine","num":1},{"id":29002,"name":"Twitch Giochi Invernali","num":2},{"id":29003,"name":"Twitch Medioevale","num":3},{"id":29004,"name":"Twitch Gangster","num":4},{"id":29005,"name":"Twitch Vandalo","num":5},{"id":29006,"name":"Twitch Borseggiatore","num":6},{"id":29007,"name":"Twitch SSW","num":7},{"id":29008,"name":"Twitch Squadra Omega","num":8}]},"DrMundo":{"id":36,"key":"DrMundo","name":"Dr. Mundo","title":"il folle di Zaun","skins":[{"id":36000,"name":"default","num":0},{"id":36001,"name":"Dr. Mundo Tossico","num":1},{"id":36002,"name":"Mr. Mundoniverso","num":2},{"id":36003,"name":"Corporate Mundo","num":3},{"id":36004,"name":"Mundo Mundo","num":4},{"id":36005,"name":"Mundo Carnefice","num":5},{"id":36006,"name":"Mundo Furia Cieca","num":6},{"id":36007,"name":"TPA Mundo","num":7},{"id":36008,"name":"Mundo Festa in Piscina","num":8},{"id":36009,"name":"Mundo El Macho","num":9}]},"Orianna":{"id":61,"key":"Orianna","name":"Orianna","title":"la signora degli ingranaggi","skins":[{"id":61000,"name":"default","num":0},{"id":61001,"name":"Orianna Gotica","num":1},{"id":61002,"name":"Orianna Bambola del Caos","num":2},{"id":61003,"name":"Orianna delle Lame","num":3},{"id":61004,"name":"TPA Orianna","num":4},{"id":61005,"name":"Orianna Prodigio Invernale","num":5},{"id":61006,"name":"Orianna Cerca Cuori","num":6},{"id":61007,"name":"Orianna Stella Oscura","num":7}]},"Evelynn":{"id":28,"key":"Evelynn","name":"Evelynn","title":"L'abbraccio agonizzante","skins":[{"id":28000,"name":"default","num":0},{"id":28001,"name":"Evelynn dell'Ombra","num":1},{"id":28002,"name":"Evelynn Masquerade","num":2},{"id":28003,"name":"Evelynn Tango","num":3},{"id":28004,"name":"Evelynn Scassinatrice","num":4}]},"RekSai":{"id":421,"key":"RekSai","name":"Rek'Sai","title":"la predatrice del Vuoto","skins":[{"id":421000,"name":"default","num":0},{"id":421001,"name":"Rek'Sai Eternum","num":1},{"id":421002,"name":"Rek'Sai Festa in Piscina","num":2}]},"Lux":{"id":99,"key":"Lux","name":"Lux","title":"la signora della luminosità","skins":[{"id":99000,"name":"default","num":0},{"id":99001,"name":"Lux Strega","num":1},{"id":99002,"name":"Lux Ladra d'Incantesimi","num":2},{"id":99003,"name":"Lux Commando","num":3},{"id":99004,"name":"Lux Imperiale","num":4},{"id":99005,"name":"Lux Legione d'Acciaio","num":5},{"id":99006,"name":"Lux Guardiana Stellare","num":6},{"id":99007,"name":"Lux Elementalista","num":7}]},"Sion":{"id":14,"key":"Sion","name":"Sion","title":"Il colosso non-morto","skins":[{"id":14000,"name":"default","num":0},{"id":14001,"name":"Sion Hextech","num":1},{"id":14002,"name":"Sion Barbaro","num":2},{"id":14003,"name":"Sion Taglialegna","num":3},{"id":14004,"name":"Sion Signore della Guerra","num":4},{"id":14005,"name":"Mecha Zero Sion","num":5}]},"Camille":{"id":164,"key":"Camille","name":"Camille","title":"l'ombra d'acciaio","skins":[{"id":164000,"name":"default","num":0},{"id":164001,"name":"Programma Camille","num":1}]},"MasterYi":{"id":11,"key":"MasterYi","name":"Master Yi","title":"lo spadaccino Wuju","skins":[{"id":11000,"name":"default","num":0},{"id":11001,"name":"Master Yi Assassino","num":1},{"id":11002,"name":"Master Yi l'Eletto","num":2},{"id":11003,"name":"Master Yi da Ionia","num":3},{"id":11004,"name":"Samurai Yi","num":4},{"id":11005,"name":"Master Yi Cacciatore di Teste","num":5},{"id":11009,"name":"PROGETTO: Yi","num":9},{"id":11010,"name":"Master Yi Lama Cosmica","num":10},{"id":11011,"name":"Yi Spada Eterna","num":11}]},"Ryze":{"id":13,"key":"Ryze","name":"Ryze","title":"il mago delle rune","skins":[{"id":13000,"name":"default","num":0},{"id":13001,"name":"Ryze Giovane","num":1},{"id":13002,"name":"Ryze Tribale","num":2},{"id":13003,"name":"Zio Ryze","num":3},{"id":13004,"name":"Ryze Trionfante","num":4},{"id":13005,"name":"Professor Ryze","num":5},{"id":13006,"name":"Ryze Zombi","num":6},{"id":13007,"name":"Ryze Cristallo Oscuro","num":7},{"id":13008,"name":"Ryze Pirata","num":8},{"id":13009,"name":"Ryze Barbabianca","num":9},{"id":13010,"name":"Ryze SKT T1","num":10}]},"Malphite":{"id":54,"key":"Malphite","name":"Malphite","title":"la scheggia del monolite","skins":[{"id":54000,"name":"default","num":0},{"id":54001,"name":"Malphite del Trifoglio","num":1},{"id":54002,"name":"Malphite Barriera Corallina","num":2},{"id":54003,"name":"Malphite di Marmo","num":3},{"id":54004,"name":"Malphite di Ossidiana","num":4},{"id":54005,"name":"Malphite Glaciale","num":5},{"id":54006,"name":"Mecha Malphite","num":6},{"id":54007,"name":"Corazzata Malphite","num":7}]},"Anivia":{"id":34,"key":"Anivia","name":"Anivia","title":"la criofenice","skins":[{"id":34000,"name":"default","num":0},{"id":34001,"name":"Anivia Spirito di Squadra","num":1},{"id":34002,"name":"Anivia Predatrice dei Cieli","num":2},{"id":34003,"name":"Anivia Cacciatrice di Noxus","num":3},{"id":34004,"name":"Anivia Hextech","num":4},{"id":34005,"name":"Anivia Nerogelo","num":5},{"id":34006,"name":"Anivia Preistorica","num":6},{"id":34007,"name":"Anivia Regina del Carnevale","num":7}]},"Shen":{"id":98,"key":"Shen","name":"Shen","title":"l'occhio del crepuscolo","skins":[{"id":98000,"name":"default","num":0},{"id":98001,"name":"Shen Ghiacciato","num":1},{"id":98002,"name":"Shen Yellowjacket","num":2},{"id":98003,"name":"Shen Chirurgo","num":3},{"id":98004,"name":"Shen Luna di Sangue","num":4},{"id":98005,"name":"Shen Signore della Guerra","num":5},{"id":98006,"name":"TPA Shen","num":6}]},"JarvanIV":{"id":59,"key":"JarvanIV","name":"Jarvan IV","title":"l'esempio di Demacia","skins":[{"id":59000,"name":"default","num":0},{"id":59001,"name":"Jarvan IV Commando","num":1},{"id":59002,"name":"Jarvan IV Ammazzadraghi","num":2},{"id":59003,"name":"Jarvan IV Forgia Oscura","num":3},{"id":59004,"name":"Jarvan IV Vittorioso","num":4},{"id":59005,"name":"Jarvan IV dei Regni in Guerra","num":5},{"id":59006,"name":"Jarvan IV Fnatic","num":6}]},"Malzahar":{"id":90,"key":"Malzahar","name":"Malzahar","title":"il profeta del Vuoto","skins":[{"id":90000,"name":"default","num":0},{"id":90001,"name":"Malzahar Visir","num":1},{"id":90002,"name":"Malzahar Principe dell'Ombra","num":2},{"id":90003,"name":"Malzahar Genio","num":3},{"id":90004,"name":"Malzahar Signore Supremo","num":4},{"id":90005,"name":"Malzahar della Nevicata","num":5},{"id":90006,"name":"Malzahar Boss da Battaglia","num":6}]},"Zac":{"id":154,"key":"Zac","name":"Zac","title":"l'arma segreta","skins":[{"id":154000,"name":"default","num":0},{"id":154001,"name":"Zac Arma Speciale","num":1},{"id":154002,"name":"Zac Festa in Piscina","num":2},{"id":154006,"name":"Zac SKT T1","num":6}]},"Gragas":{"id":79,"key":"Gragas","name":"Gragas","title":"il provocatore delle masse","skins":[{"id":79000,"name":"default","num":0},{"id":79001,"name":"Gragas Sommozzatore","num":1},{"id":79002,"name":"Gragas Campagnolo","num":2},{"id":79003,"name":"Santa Gragas","num":3},{"id":79004,"name":"Gragas Nobiluomo","num":4},{"id":79005,"name":"Gragas Vandalo","num":5},{"id":79006,"name":"Gragas Oktoberfest","num":6},{"id":79007,"name":"Gragas Tifoso Sfegatato ","num":7},{"id":79008,"name":"Gragas Fnatic","num":8},{"id":79009,"name":"Gragas Fracassabotti","num":9}]}},"type":"champion","version":"7.22.1"}